lemo_vocabulate/__init__.py
lemo_vocabulate/core.py
lemo_vocabulate/dictionary.py
lemo_vocabulate/stopwords.py
lemo_vocabulate/tokenizer.py
lemo_vocabulate/data/AEV_Dict.csv
lemo_vocabulate/data/stopwords.txt
lemo_vocabulate-1.0.2.dist-info/licenses/LICENSE
lemo_vocabulate-1.0.2.dist-info/METADATA
lemo_vocabulate-1.0.2.dist-info/WHEEL
lemo_vocabulate-1.0.2.dist-info/top_level.txt
lemo_vocabulate-1.0.2.dist-info/RECORD
