Metadata-Version: 2.4
Name: lemo-vocabulate
Version: 1.0.2
Summary: Dictionary-based text analysis tool for emotion and sentiment analysis. Python port of Vocabulate (Vine et al., 2020).
Author-email: Steven Mesquiti <sm9518@princeton.edu>
License: MIT License
Project-URL: Homepage, https://github.com/Bushel-of-Lemons/LEMO_Vocabulate
Project-URL: Issues, https://github.com/Bushel-of-Lemons/LEMO_Vocabulate/issues
Classifier: Programming Language :: Python :: 3
Classifier: Programming Language :: Python :: 3.8
Classifier: License :: OSI Approved :: MIT License
Classifier: Operating System :: OS Independent
Requires-Python: >=3.8
License-File: LICENSE
Requires-Dist: pandas>=1.3.0
Requires-Dist: tqdm>=4.62.0
Dynamic: license-file
